{
  "kind": "collectionType",
  "collectionName": "collaborators",
  "info": {
    "singularName": "collaborator",
    "pluralName": "collaborators",
    "displayName": "Collaborator",
    "description": "Partner organizations and collaborator logos"
  },
  "options": {
    "draftAndPublish": false
  },
  "pluginOptions": {},
  "attributes": {
    "name": {
      "type": "string",
      "required": true
    },
    "url": {
      "type": "string"
    },
    "logo": {
      "type": "media",
      "multiple": false,
      "allowedTypes": ["images"]
    }
  }
}
